Metadata-Version: 1.1
Name: kursywalut
Version: 0.2.0
Summary: Program do wyświetlania i przeliczania aktualnych kursów walut.
Home-page: https://github.com/bartgee/kursywalut
Author: Bart Grzybicki
Author-email: bgrzybicki@gmail.com
License: GNU General Public License v3
Keywords: kursywalut
Platform: UNKNOWN
Classifier: Development Status :: 2 - Pre-Alpha
Classifier: Intended Audience :: Developers
Classifier: License :: OSI Approved :: GNU General Public License v3 (GPLv3)
Classifier: Natural Language :: English
Classifier: Programming Language :: Python :: 2
Classifier: Programming Language :: Python :: 2.7
Classifier: Programming Language :: Python :: 3
Classifier: Programming Language :: Python :: 3.4
Classifier: Programming Language :: Python :: 3.5
Classifier: Programming Language :: Python :: 3.6
Classifier: Programming Language :: Python :: 3.7
